{
  "repo": "lance-format/lance",
  "number": 7511,
  "sha": "f2596e9b87e5b03223dd33878a4767237c78ec61",
  "soap": "RE-REVIEW \u00b7 lance-format/lance#7511 \u2014 docs(arrow): add SAFETY comments to lance-arrow unsafe blocks\nreviewed cdc25d7f \u2192 f2596e9b  (1 commit, 1 file)\ndomain: rust/lance-arrow\n\n# SOAP\n\n## Subjective\nAuthor (LuciferYang, core) pushed one commit since my last review. The PR's\npurpose is documentation/hardening: annotate the five `unsafe` blocks in\n`lance-arrow` with `// SAFETY:` invariant chains, gate little-endian at the\ncrate root with `compile_error!`, add a `debug_assert` on the 2-byte alignment\nprecondition of `as_slice`, and document the `# Panics`/`# Preconditions`\ncontract on the float traits. The new commit is the one piece I asked for in my\nprior review: turn the project's \"every unsafe needs a SAFETY comment\" rule into\na mechanically-enforced clippy lint.\n\n## Objective\nDelta `cdc25d7f...f2596e9b`, scoped to the PR's own files (0 off-branch files\nexcluded):\n\n- `rust/lance-arrow/src/lib.rs` (+2/-0): adds\n  `#![warn(clippy::undocumented_unsafe_blocks)]` at the crate root, immediately\n  after the module docstring and before the `compile_error!` little-endian gate.\n\nVerification against ground truth:\n- Lint placement is correct (crate root attribute, ahead of items).\n- CI `clippy` job PASSES at head, so the new lint does not fire on the existing\n  code \u2014 i.e. every in-scope unsafe block already carries a SAFETY comment\n  (confirmed by reading bfloat16.rs/deepcopy.rs: 5 documented unsafe blocks; the\n  one pre-existing block at bfloat16.rs:102 uses lowercase `// Safety:`, which\n  the lint accepts case-insensitively, and is untouched by this PR).\n- `format`, `rustdoc`, MSRV, mac/windows/linux-arm builds all PASS.\n- One red check: `linux-build` FAILS \u2014 but the failure is a rustc INTERNAL\n  COMPILER ERROR (ICE) while compiling `lance-index` (lib test), not a defect in\n  this PR. The compiler panicked in the trait solver (`check_opaque` /\n  `evaluate_obligation`) and emitted a `rustc-ice-*.txt` bug-report note. It is\n  unrelated to lance-arrow and is infra/toolchain flake; a re-run should clear it.\n\n## Assessment\n\n### Section A \u2014 Conditions ledger (0 of 0 met)\nNo blocking conditions were reconstructed from my prior review \u2014 I left no\n`issue(blocking)` comments on this PR. The clippy-lint request from my earlier\nreview was a non-blocking suggestion, and the author has now addressed it\nexactly (see lib.rs delta). Nothing outstanding to verify.\n\n### Section B \u2014 Fresh-eyes delta\nThe only change since last review is the two-line lint addition. It is sound,\nwell-placed, and consistent with the rest of the crate (clippy is green at\nhead). No new findings. No regressions introduced by the delta.\n\nThe lone red CI check is a rustc ICE in an unrelated crate, not attributable to\nthis change.\n\n## Plan\nRECOMMENDATION: approve\n- Section A: nothing outstanding (no conditions).\n- Section B: no new concerns; delta is the requested lint and it is correct.\n- Non-blocking note for the attending: the red `linux-build` is a rustc ICE in\n  `lance-index`, unrelated to this PR \u2014 recommend re-running that one job rather\n  than treating it as a blocker.\n\nconfidence: high \u00b7 what would make this wrong: if the `linux-build` ICE turned\nout to be deterministically triggered by the new crate-root attribute rather\nthan a transient compiler crash \u2014 but it fails in `lance-index` (a different\ncrate that does not depend on this attribute) and the dedicated `clippy`/`format`\n/`rustdoc` jobs on lance-arrow are green, so this is very unlikely.\n\nDRAFTED COMMENTS: none (no blocking findings; approve recommendation).\n",
  "cached_at": "2026-06-30T15:22:15Z"
}